b8/.gitignore
b8/__init__.py
b8/app.py
b8/buffers.py
b8/configs.py
b8/files.py
b8/logs.py
b8/paths.py
b8/service.py
b8/terminals.py
b8/ui.py
b8/version.py
b8/vim.py
b8-0.2.3.dist-info/entry_points.txt
b8-0.2.3.dist-info/WHEEL
b8-0.2.3.dist-info/METADATA
b8-0.2.3.dist-info/RECORD
