Metadata-Version: 1.1
Name: b8
Version: 0.2.3
Summary: b8, Bominade Ultralight NeoVim-based IDE
Home-page: https://gitlab.com/afshar-oss/b8
Author: Ali Afshar
Author-email: aafshar@gmail.com
